[{"users":[],"tasks":[],"lists":[],"name":"Mercure"},{"users":[],"tasks":[],"lists":[],"name":"Vénus"},{"users":[],"tasks":[],"lists":[],"name":"Terre"},{"users":[],"tasks":[],"lists":[],"name":"Mars"},{"users":[],"tasks":[],"lists":[],"name":"Jupiter"},{"users":[{"name":"Amir","tasks":[{"value":"Passer le balais","status":1},{"value":"Vaiselle","status":1}],"count":[]},{"name":"Leo","tasks":[{"value":"Faire les courses","status":1},{"value":"Machine à lavée","status":1}],"count":[]},{"name":"Cedric","tasks":[],"count":[]},{"name":"Valentin","tasks":[],"count":[]},{"name":"Polo","tasks":[{"value":"Rincer le lavabo","status":1}],"lists":[]}],"lists":[{"name":"liste de course","items":[{"value":"Tomate","count":1,"status":0},{"value":"Lait","count":1,"status":1},{"value":"Oeuf","count":6,"status":0}]},{"name":"liste de soirée 42","items":[{"value":"Chips","count":2,"status":0},{"value":"Bière","count":3,"status":1},{"value":"Pizza","count":4,"status":0}]},{"name":"la semaine du classico","items":[{"value":"Tomate","count":1,"status":0},{"value":"Lait","count":1,"status":1},{"value":"Oeuf","count":6,"status":0},{"value":"Céréales","count":1,"status":0},{"value":"ToutLeBonheurduMonde","count":0,"status":0}]}],"tasks":[{"value":"Passer le balais","status":1},{"value":"Vaisselle","status":1},{"value":"Faire les courses","status":2},{"value":"Machine à lavée","status":1},{"value":"Changer la litière","status":2},{"value":"Nettoyer la douche","status":0},{"value":"Payer internet","status":2},{"value":"machin","status":0}],"name":"Saturne"}]